{
  "tables": [
    {
      "tableName": "merchant",
      "columns": [
        {
          "name": "name",
          "dataType": "varchar(500)",
          "columnType": "label",
          "isIndexed": true
        },
        {
          "name": "image_url",
          "dataType": "varchar(500)",
          "columnType": "label",
          "isNullable": true
        },
        {
          "name": "status",
          "dataType": "varchar(50)",
          "columnType": "label",
          "defaultValue": "'active'"
        }
      ]
    },
    {
      "tableName": "integration",
      "columns": [
        {
          "name": "name",
          "dataType": "varchar(100)",
          "columnType": "label",
          "isIndexed": true
        },
        {
          "name": "icon",
          "dataType": "varchar(100)",
          "columnType": "label",
          "defaultValue": "'devicon-devicon-plain'"
        },
        {
          "name": "color",
          "dataType": "varchar(10)",
          "columnType": "color",
          "defaultValue": "'#708ad8'"
        },
        {
          "name": "description",
          "dataType": "text",
          "columnType": "content",
          "isNullable": true
        },
        {
          "name": "language",
          "dataType": "varchar(100)",
          "columnType": "label",
          "isIndexed": true
        },
        {
          "name": "stack",
          "dataType": "varchar(100)",
          "columnType": "label",
          "isIndexed": true
        },
        {
          "name": "api_type",
          "dataType": "varchar(100)",
          "columnType": "label",
          "isNullable": true,
          "isIndexed": true
        },
        {
          "name": "api_sub_type",
          "dataType": "varchar(100)",
          "columnType": "label",
          "isNullable": true,
          "isIndexed": true
        },
        {
          "name": "change_set",
          "dataType": "text",
          "columnType": "json",
          "isIndexed": true
        }
      ]
    },
    {
      "tableName": "tag",
      "columns": [
        {
          "name": "label",
          "dataType": "varchar(100)",
          "columnType": "label",
          "isIndexed": true
        }
      ]
    }
  ],
  "relations": [
    {
      "subject": "integration",
      "relation": "belongs_to",
      "object": "merchant"
    },
    {
      "subject": "integration",
      "relation": "has_many",
      "object": "tag"
    }
  ]
}
